module_scan/__init__.py
module_scan/scan.py
module_scan-1.0.0.dist-info/LICENSE
module_scan-1.0.0.dist-info/METADATA
module_scan-1.0.0.dist-info/WHEEL
module_scan-1.0.0.dist-info/entry_points.txt
module_scan-1.0.0.dist-info/top_level.txt
module_scan-1.0.0.dist-info/RECORD
