Metadata-Version: 2.1
Name: module-scan
Version: 1.0.0
Summary: Repository scanner for module imports
Home-page: https://github.com/cetcs92/module-scanner
Author: Rajesh Gopinathapai, Akshad Pai
Author-email: mgrajesh@hotmail.com, akshadpai01@gmail.com
Project-URL: Bug Tracker, https://github.com/cetcs92/module-scanner/issues
Classifier: Programming Language :: Python :: 3
Classifier: License :: OSI Approved :: MIT License
Classifier: Operating System :: OS Independent
Requires-Python: >=3.6
License-File: LICENSE
